nupic-1.0.5-py2.7-nspkg.pth
nupic/movingaverage.capnp
nupic/serializable.py
nupic/simple_server.py
nupic/utils.py
nupic/algorithms/__init__.py
nupic/algorithms/anomaly.py
nupic/algorithms/anomaly_likelihood.capnp
nupic/algorithms/anomaly_likelihood.py
nupic/algorithms/backtracking_tm.capnp
nupic/algorithms/backtracking_tm.py
nupic/algorithms/backtracking_tm_cpp.capnp
nupic/algorithms/backtracking_tm_cpp.py
nupic/algorithms/backtracking_tm_shim.py
nupic/algorithms/connections.py
nupic/algorithms/fdrutilities.py
nupic/algorithms/knn_classifier.capnp
nupic/algorithms/knn_classifier.py
nupic/algorithms/sdr_classifier.py
nupic/algorithms/sdr_classifier_diff.py
nupic/algorithms/sdr_classifier_factory.py
nupic/algorithms/spatial_pooler.py
nupic/algorithms/temporal_memory.py
nupic/algorithms/temporal_memory_shim.capnp
nupic/algorithms/temporal_memory_shim.py
nupic/algorithms/utils.py
nupic/algorithms/monitor_mixin/__init__.py
nupic/algorithms/monitor_mixin/metric.py
nupic/algorithms/monitor_mixin/monitor_mixin_base.py
nupic/algorithms/monitor_mixin/plot.py
nupic/algorithms/monitor_mixin/temporal_memory_monitor_mixin.py
nupic/algorithms/monitor_mixin/trace.py
nupic/data/__init__.py
nupic/data/aggregator.py
nupic/data/category_filter.py
nupic/data/dict_utils.py
nupic/data/field_meta.py
nupic/data/file_record_stream.py
nupic/data/filters.py
nupic/data/function_source.py
nupic/data/inference_shifter.py
nupic/data/json_helpers.py
nupic/data/record_stream.py
nupic/data/sorter.py
nupic/data/stats.py
nupic/data/stats_v2.py
nupic/data/stream_reader.py
nupic/data/testSchema.json
nupic/data/utils.py
nupic/data/generators/__init__.py
nupic/data/generators/anomalyzer.py
nupic/data/generators/data_generator.py
nupic/data/generators/distributions.py
nupic/data/generators/pattern_machine.py
nupic/data/generators/sequence_machine.py
nupic/database/__init__.py
nupic/database/client_jobs_dao.py
nupic/database/connection.py
nupic-1.0.5.dist-info/DESCRIPTION.rst
nupic-1.0.5.dist-info/METADATA
nupic-1.0.5.dist-info/RECORD
nupic-1.0.5.dist-info/WHEEL
nupic-1.0.5.dist-info/metadata.json
nupic-1.0.5.dist-info/namespace_packages.txt
nupic-1.0.5.dist-info/top_level.txt
