Metadata-Version: 2.0
Name: nupic
Version: 1.0.5
Summary: Numenta Platform for Intelligent Computing
Home-page: https://github.com/numenta/nupic
Author: Numenta
Author-email: help@numenta.org
License: UNKNOWN
Platform: UNKNOWN
Classifier: Programming Language :: Python
Classifier: Programming Language :: Python :: 2
Classifier: License :: OSI Approved :: GNU Affero General Public License v3 or later (AGPLv3+)
Classifier: Operating System :: MacOS :: MacOS X
Classifier: Operating System :: POSIX :: Linux
Classifier: Operating System :: Microsoft :: Windows
Classifier: Development Status :: 5 - Production/Stable
Classifier: Environment :: Console
Classifier: Intended Audience :: Science/Research
Classifier: Topic :: Scientific/Engineering :: Artificial Intelligence
Requires-Dist: DBUtils (==1.1)
Requires-Dist: PyMySQL (==0.6.2)
Requires-Dist: PyYAML (==3.10)
Requires-Dist: asteval (==0.9.1)
Requires-Dist: coverage (==3.7.1)
Requires-Dist: mock (==1.0.1)
Requires-Dist: numpy (==1.12.1)
Requires-Dist: nupic.bindings (==1.0.6)
Requires-Dist: ordereddict (==1.1)
Requires-Dist: prettytable (==0.7.2)
Requires-Dist: psutil (==1.0.1)
Requires-Dist: pyproj (==1.9.3)
Requires-Dist: pytest (==3.0.7)
Requires-Dist: pytest-cov (==2.5.0)
Requires-Dist: pytest-xdist (==1.16.0)
Requires-Dist: python-dateutil (==2.1)
Requires-Dist: unittest2 (==0.5.1)
Requires-Dist: validictory (==0.9.1)
Requires-Dist: pycapnp (==0.6.3); platform_system=='Linux' or platform_system=='Darwin'
Provides-Extra: capnp
Provides-Extra: viz
Requires-Dist: matplotlib; extra == 'viz'
Requires-Dist: networkx; extra == 'viz'
Requires-Dist: pygraphviz; extra == 'viz'
